space_avenger/__init__.py
space_avenger/main.py
space_avenger/assets/background_music.mp3
space_avenger/assets/bullet.png
space_avenger/assets/enemy-flyer.png
space_avenger/assets/enemy-seeker.png
space_avenger/assets/explosion.png
space_avenger/assets/explosion_sound.mp3
space_avenger/assets/final-round.png
space_avenger/assets/game_lose_sound.mp3
space_avenger/assets/game_win_sound.mp3
space_avenger/assets/message-lose.png
space_avenger/assets/message-win.png
space_avenger/assets/spaceship.png
space_avenger/assets/stars-bg.png
space_avenger-0.1.4.dist-info/METADATA
space_avenger-0.1.4.dist-info/WHEEL
space_avenger-0.1.4.dist-info/entry_points.txt
space_avenger-0.1.4.dist-info/top_level.txt
space_avenger-0.1.4.dist-info/RECORD
